revolut_merchant/__init__.py
revolut_merchant/exceptions.py
revolut_merchant/utils.py
revolut_merchant_python-0.0.4.dist-info/LICENSE
revolut_merchant_python-0.0.4.dist-info/METADATA
revolut_merchant_python-0.0.4.dist-info/WHEEL
revolut_merchant_python-0.0.4.dist-info/top_level.txt
revolut_merchant_python-0.0.4.dist-info/RECORD
