Metadata-Version: 2.1
Name: revolut-merchant-python
Version: 0.0.4
Summary: Revolut Merchant API client for Python
Home-page: https://github.com/the-veloper/revolut-merchant-python/
Author: Georgi Georgiev
Author-email: g.georgiev@theorigamicorporation.com
License: Apache License 2.0
Keywords: revolut payments merchant api client
Classifier: Development Status :: 4 - Beta
Classifier: Intended Audience :: Developers
Classifier: License :: OSI Approved :: Apache Software License
Classifier: Operating System :: OS Independent
Classifier: Programming Language :: Python
Classifier: Programming Language :: Python :: 2.7
Classifier: Programming Language :: Python :: 3.6
Classifier: Programming Language :: Python :: 3.7
License-File: LICENSE
Requires-Dist: python-dateutil
Requires-Dist: requests (>=2.0)
Requires-Dist: pyjwt (>=1.7)
